{
  "A": "UF Goal",
  "B": "UF Volume",
  "C": "UF rate",
  "D": "BF rate",
  "E": "Heparin rate",
  "F": "Dialysate temperature",
  "G": "Total conductivity",
  "H": "Venous pressure",
  "I": "Dialysate flow pressure",
  "J": "TMP",
  "K": "Treatment time",
  "L": "Dialysate flow rate",
  "a": "Dialysate temperature alarm",
  "b": "Total conductivity alarm",
  "c": "Venous pressure alarm",
  "d": "Dialysate flow pressure alarm",
  "e": "TMP alarm ",
  "f": "Air alarm",
  "g": "Blood leak alarm",
  "h": "Other alarm",
  "M": "Under treatment state",
  "N": "Treatment mode",
  "O": "Substitution goal",
  "P": "Substitution volume",
  "Q": "Substitution rate",
  "R": "Substitution temperature",
  "S": "Blood pressure measurement time",
  "T": "Systolic blood pressure",
  "U": "Diastolic blood pressure",
  "V": "Pulse",
  "i": "Blood pressure alarm",
  "W": "Total Heparin Infused"
}